<ParameterList>
    <Parameter name="Enable Delayed Solver Construction" type="bool" value="false"/>
    <Parameter name="Linear Solver Type" type="string" value="Amesos"/>
    <ParameterList name="Linear Solver Types">
      <ParameterList name="Amesos">
        <ParameterList name="Amesos Settings">
        </ParameterList>
      </ParameterList>
    </ParameterList>
    <Parameter name="Preconditioner Type" type="string" value="ML"/>
    <ParameterList name="Preconditioner Types">
      <ParameterList name="ML">
        <Parameter name="Base Method Defaults" type="string" value="SA"/>
        <ParameterList name="ML Settings">
          <Parameter name="default values" type="string" value="SA"/>
          <Parameter name="cycle applications" type="int" value="8"/>
          <Parameter name="coarse: type" type="string" value="Amesos-KLU"/>
          <Parameter name="max levels" type="int" value="6"/>
        </ParameterList>
      </ParameterList>
    </ParameterList>
</ParameterList>

