<ParameterList>
  <Parameter name="Linear Solver Type" type="string" value="Belos"/>
  <ParameterList name="Linear Solver Types">
    <ParameterList name="Belos">
      <Parameter name="Solver Type" type="string" value="Block GMRES"/>
      <ParameterList name="Solver Types">
        <ParameterList name="Block GMRES">
          <Parameter name="Block Size" type="int" value="1"/>
          <Parameter name="Convergence Tolerance" type="double" value="1e-13"/>
          <Parameter name="Num Blocks" type="int" value="300"/>
  	  <Parameter name="Output Frequency" type="int" value="1"/>
  	  <Parameter name="Show Maximum Residual Norm Only" type="bool" value="1"/>
          <Parameter name="Maximum Iterations" type="int" value="400"/>
        </ParameterList>
      </ParameterList>
    </ParameterList>
  </ParameterList>
  <Parameter name="Preconditioner Type" type="string" value="Ifpack2"/>
  <ParameterList name="Preconditioner Types">
    <ParameterList name="Ifpack2">
      <Parameter name="Prec Type" type="string" value="SCHWARZ"/>
      <Parameter name="Overlap" type="int" value="1"/>
      <ParameterList name="Ifpack2 Settings">
        <Parameter name="fact: iluk level-of-fill" type="int" value="2"/>
      </ParameterList>
    </ParameterList>
  </ParameterList>
</ParameterList>

